LICENSE
MANIFEST.in
README.rst
setup.cfg
setup.py
rshell/__init__.py
rshell/command_line.py
rshell/dfutils.py
rshell/getch.py
rshell/main.py
rshell/pyboard.py
rshell/test.py
rshell/version.py
rshell.egg-info/PKG-INFO
rshell.egg-info/SOURCES.txt
rshell.egg-info/dependency_links.txt
rshell.egg-info/entry_points.txt
rshell.egg-info/requires.txt
rshell.egg-info/top_level.txt
tests/hello.py
tests/make_all_bytes.py
tests/tree_cmp.py