Metadata-Version: 2.1
Name: rshell
Version: 0.0.34
Summary: A remote shell for working with MicroPython boards.
Home-page: https://github.com/dhylands/rshell
Author: Dave Hylands
Author-email: dhylands@gmail.com
License: MIT
Download-URL: https://github.com/dhylands/rshell/tarball/v0.0.1
Keywords: micropython shell
Platform: UNKNOWN
Classifier: Development Status :: 3 - Alpha
Classifier: Environment :: Console
Classifier: Intended Audience :: Developers
Classifier: License :: OSI Approved :: MIT License
Classifier: Natural Language :: English
Classifier: Operating System :: POSIX :: Linux
Classifier: Programming Language :: Python
Classifier: Programming Language :: Python :: 3
Classifier: Topic :: Software Development :: Embedded Systems
Classifier: Topic :: System :: Shells
Classifier: Topic :: Terminals :: Serial
Classifier: Topic :: Utilities
License-File: LICENSE
